dbt/adapters/spark/connections.py
dbt/adapters/spark/emr.py
dbt_spark_emr_serverless_addons-0.1.5.dist-info/licenses/LICENSE
dbt_spark_emr_serverless_addons-0.1.5.dist-info/METADATA
dbt_spark_emr_serverless_addons-0.1.5.dist-info/WHEEL
dbt_spark_emr_serverless_addons-0.1.5.dist-info/top_level.txt
dbt_spark_emr_serverless_addons-0.1.5.dist-info/RECORD
