Metadata-Version: 2.4
Name: dbt-spark-emr-serverless-addons
Version: 0.1.5
Summary: A dbt-spark adapter using Livy to connect to Spark clusters
Author-email: Thanh Tran <thanhmt0612@gmail.com>
Maintainer-email: Thanh Tran <thanhmt0612@gmail.com>
License: MIT License
Project-URL: Repository, https://github.com/kalliope-product/dbt-spark-emr-serverless.git
Project-URL: Issues, https://github.com/kalliope-product/dbt-spark-emr-serverless/issues
Requires-Python: >=3.10.0
License-File: LICENSE
Requires-Dist: dbt-spark<2.0,>=1.5.0
Requires-Dist: httpx<1.0.0,>=0.24.0
Requires-Dist: boto3<2.0.0,>=1.26.0
Dynamic: license-file
